[
  {
    "line": 2,
    "elements": [
      {
        "line": 15,
        "name": "Comportamiento",
        "description": "",
        "id": "med-126---obligatorios-01---validar-la-lista-desplegable-del-combo-tipo-de-responsable;comportamiento;;2",
        "after": [
          {
            "result": {
              "duration": 118351,
              "status": "passed"
            },
            "match": {
              "location": "RpnCalculatorStepdefs.after(Scenario)"
            }
          }
        ],
        "type": "scenario",
        "keyword": "Scenario Outline",
        "steps": [
          {
            "result": {
              "duration": 7817774223,
              "status": "passed"
            },
            "line": 5,
            "name": "Obligatorio a Ingreso al sistema Sumes",
            "match": {
              "location": "Steps01.obligatorio_a_Ingreso_al_sistema_Sumes()"
            },
            "keyword": "Given "
          },
          {
            "result": {
              "duration": 110139997,
              "status": "passed"
            },
            "line": 6,
            "name": "Obligatorio a Usuario: mveron",
            "match": {
              "arguments": [
                {
                  "val": "mveron",
                  "offset": 23
                }
              ],
              "location": "Steps01.obligatorio_a_Usuario_mveron(String)"
            },
            "keyword": "And "
          },
          {
            "result": {
              "duration": 79143228,
              "status": "passed"
            },
            "line": 7,
            "name": "Obligatorio a Pass: Mv190319",
            "match": {
              "arguments": [
                {
                  "val": "Mv190319",
                  "offset": 20
                }
              ],
              "location": "Steps01.obligatorio_a_Pass_Mv(String)"
            },
            "keyword": "And "
          },
          {
            "result": {
              "duration": 4902283984,
              "status": "passed"
            },
            "line": 8,
            "name": "Obligatorio a Seleccion alta de responsable de pago",
            "match": {
              "location": "Steps01.obligatorio_a_Seleccion_alta_de_responsable_de_pago()"
            },
            "keyword": "And "
          },
          {
            "result": {
              "duration": 5659205841,
              "status": "passed"
            },
            "line": 9,
            "name": "Obligatorio a la pantalla Alta de responsible de pago desplegada",
            "match": {
              "location": "Steps01.obligatorio_a_la_pantalla_Alta_de_responsible_de_pago_desplegada()"
            },
            "keyword": "And "
          },
          {
            "result": {
              "duration": 1884316,
              "status": "passed"
            },
            "line": 10,
            "name": "Obligatorio a seleciona el campo Tipo de Responsable",
            "match": {
              "location": "Steps01.obligatorio_a_seleciona_el_campo_Tipo_de_Responsable()"
            },
            "keyword": "When "
          },
          {
            "result": {
              "duration": 3255662171,
              "status": "passed"
            },
            "line": 11,
            "name": "Obligatorio a A Selecciono Empresa Empresa",
            "match": {
              "arguments": [
                {
                  "val": "Empresa",
                  "offset": 35
                }
              ],
              "location": "Steps01.obligatorio_a_A_Selecciono_Empresa_Empresa(String)"
            },
            "keyword": "When "
          }
        ],
        "tags": [
          {
            "name": "@foo"
          }
        ]
      },
      {
        "line": 16,
        "name": "Comportamiento",
        "description": "",
        "id": "med-126---obligatorios-01---validar-la-lista-desplegable-del-combo-tipo-de-responsable;comportamiento;;3",
        "after": [
          {
            "result": {
              "duration": 41696,
              "status": "passed"
            },
            "match": {
              "location": "RpnCalculatorStepdefs.after(Scenario)"
            }
          }
        ],
        "type": "scenario",
        "keyword": "Scenario Outline",
        "steps": [
          {
            "result": {
              "duration": 14526656106,
              "status": "passed"
            },
            "line": 5,
            "name": "Obligatorio a Ingreso al sistema Sumes",
            "match": {
              "location": "Steps01.obligatorio_a_Ingreso_al_sistema_Sumes()"
            },
            "keyword": "Given "
          },
          {
            "result": {
              "duration": 74339904,
              "status": "passed"
            },
            "line": 6,
            "name": "Obligatorio a Usuario: mveron",
            "match": {
              "arguments": [
                {
                  "val": "mveron",
                  "offset": 23
                }
              ],
              "location": "Steps01.obligatorio_a_Usuario_mveron(String)"
            },
            "keyword": "And "
          },
          {
            "result": {
              "duration": 79251316,
              "status": "passed"
            },
            "line": 7,
            "name": "Obligatorio a Pass: Mv190319",
            "match": {
              "arguments": [
                {
                  "val": "Mv190319",
                  "offset": 20
                }
              ],
              "location": "Steps01.obligatorio_a_Pass_Mv(String)"
            },
            "keyword": "And "
          },
          {
            "result": {
              "duration": 4866570169,
              "status": "passed"
            },
            "line": 8,
            "name": "Obligatorio a Seleccion alta de responsable de pago",
            "match": {
              "location": "Steps01.obligatorio_a_Seleccion_alta_de_responsable_de_pago()"
            },
            "keyword": "And "
          },
          {
            "result": {
              "duration": 6059078702,
              "status": "passed"
            },
            "line": 9,
            "name": "Obligatorio a la pantalla Alta de responsible de pago desplegada",
            "match": {
              "location": "Steps01.obligatorio_a_la_pantalla_Alta_de_responsible_de_pago_desplegada()"
            },
            "keyword": "And "
          },
          {
            "result": {
              "duration": 203025,
              "status": "passed"
            },
            "line": 10,
            "name": "Obligatorio a seleciona el campo Tipo de Responsable",
            "match": {
              "location": "Steps01.obligatorio_a_seleciona_el_campo_Tipo_de_Responsable()"
            },
            "keyword": "When "
          },
          {
            "result": {
              "duration": 3193423270,
              "status": "passed"
            },
            "line": 11,
            "name": "Obligatorio a A Selecciono Empresa Externo",
            "match": {
              "arguments": [
                {
                  "val": "Externo",
                  "offset": 35
                }
              ],
              "location": "Steps01.obligatorio_a_A_Selecciono_Empresa_Empresa(String)"
            },
            "keyword": "When "
          }
        ],
        "tags": [
          {
            "name": "@foo"
          }
        ]
      },
      {
        "line": 17,
        "name": "Comportamiento",
        "description": "",
        "id": "med-126---obligatorios-01---validar-la-lista-desplegable-del-combo-tipo-de-responsable;comportamiento;;4",
        "after": [
          {
            "result": {
              "duration": 43941,
              "status": "passed"
            },
            "match": {
              "location": "RpnCalculatorStepdefs.after(Scenario)"
            }
          }
        ],
        "type": "scenario",
        "keyword": "Scenario Outline",
        "steps": [
          {
            "result": {
              "duration": 12854171524,
              "status": "passed"
            },
            "line": 5,
            "name": "Obligatorio a Ingreso al sistema Sumes",
            "match": {
              "location": "Steps01.obligatorio_a_Ingreso_al_sistema_Sumes()"
            },
            "keyword": "Given "
          },
          {
            "result": {
              "duration": 73250047,
              "status": "passed"
            },
            "line": 6,
            "name": "Obligatorio a Usuario: mveron",
            "match": {
              "arguments": [
                {
                  "val": "mveron",
                  "offset": 23
                }
              ],
              "location": "Steps01.obligatorio_a_Usuario_mveron(String)"
            },
            "keyword": "And "
          },
          {
            "result": {
              "duration": 81401201,
              "status": "passed"
            },
            "line": 7,
            "name": "Obligatorio a Pass: Mv190319",
            "match": {
              "arguments": [
                {
                  "val": "Mv190319",
                  "offset": 20
                }
              ],
              "location": "Steps01.obligatorio_a_Pass_Mv(String)"
            },
            "keyword": "And "
          },
          {
            "result": {
              "duration": 4257317483,
              "status": "passed"
            },
            "line": 8,
            "name": "Obligatorio a Seleccion alta de responsable de pago",
            "match": {
              "location": "Steps01.obligatorio_a_Seleccion_alta_de_responsable_de_pago()"
            },
            "keyword": "And "
          },
          {
            "result": {
              "duration": 5855762048,
              "status": "passed"
            },
            "line": 9,
            "name": "Obligatorio a la pantalla Alta de responsible de pago desplegada",
            "match": {
              "location": "Steps01.obligatorio_a_la_pantalla_Alta_de_responsible_de_pago_desplegada()"
            },
            "keyword": "And "
          },
          {
            "result": {
              "duration": 394504,
              "status": "passed"
            },
            "line": 10,
            "name": "Obligatorio a seleciona el campo Tipo de Responsable",
            "match": {
              "location": "Steps01.obligatorio_a_seleciona_el_campo_Tipo_de_Responsable()"
            },
            "keyword": "When "
          },
          {
            "result": {
              "duration": 3197208581,
              "status": "passed"
            },
            "line": 11,
            "name": "Obligatorio a A Selecciono Empresa Grupo",
            "match": {
              "arguments": [
                {
                  "val": "Grupo",
                  "offset": 35
                }
              ],
              "location": "Steps01.obligatorio_a_A_Selecciono_Empresa_Empresa(String)"
            },
            "keyword": "When "
          }
        ],
        "tags": [
          {
            "name": "@foo"
          }
        ]
      }
    ],
    "name": "Med 126 - Obligatorios 01 - Validar la lista desplegable del combo Tipo de Responsable",
    "description": "",
    "id": "med-126---obligatorios-01---validar-la-lista-desplegable-del-combo-tipo-de-responsable",
    "keyword": "Feature",
    "uri": "cucumber/examples/java/calculator/PruebaObligatorio01.feature",
    "tags": [
      {
        "name": "@foo",
        "type": "Tag",
        "location": {
          "line": 1,
          "column": 1
        }
      }
    ]
  },
  {
    "line": 1,
    "elements": [
      {
        "before": [
          {
            "output": [
              "Runs before scenarios *not* tagged with @foo"
            ],
            "result": {
              "duration": 115465,
              "status": "passed"
            },
            "match": {
              "location": "RpnCalculatorStepdefs.before(Scenario)"
            }
          }
        ],
        "line": 13,
        "name": "Comportamiento",
        "description": "",
        "id": "med-127---obligatorios-02---validar-comportamiento-de-la-pantalla-segun-seleccion-tipo-de-responsable-\u003d-empresa;comportamiento;;2",
        "type": "scenario",
        "keyword": "Scenario Outline",
        "steps": [
          {
            "result": {
              "duration": 10922759050,
              "status": "passed"
            },
            "line": 4,
            "name": "Obligatorio b Ingreso al sistema Sumes",
            "match": {
              "location": "Steps02.obligatorio_b_Ingreso_al_sistema_Sumes()"
            },
            "keyword": "Given "
          },
          {
            "result": {
              "error_message": "cucumber.api.PendingException: TODO: implement me\r\n\tat cucumber.examples.java.calculator.Steps02.obligatorio_b_Usuario_mveron(Steps02.java:35)\r\n\tat ✽.Obligatorio b Usuario: mveron(cucumber/examples/java/calculator/PruebaObligatorio02.feature:5)\r\n",
              "duration": 1588278,
              "status": "pending"
            },
            "line": 5,
            "name": "Obligatorio b Usuario: mveron",
            "match": {
              "location": "Steps02.obligatorio_b_Usuario_mveron()"
            },
            "keyword": "And "
          },
          {
            "line": 6,
            "name": "Obligatorio b Pass: Mv190319",
            "keyword": "And "
          }
        ]
      }
    ],
    "name": "Med 127 - Obligatorios 02 - Validar comportamiento de la pantalla segun seleccion tipo de responsable \u003d Empresa",
    "description": "",
    "id": "med-127---obligatorios-02---validar-comportamiento-de-la-pantalla-segun-seleccion-tipo-de-responsable-\u003d-empresa",
    "keyword": "Feature",
    "uri": "cucumber/examples/java/calculator/PruebaObligatorio02.feature",
    "tags": []
  },
  {
    "line": 1,
    "elements": [
      {
        "before": [
          {
            "output": [
              "Runs before scenarios *not* tagged with @foo"
            ],
            "result": {
              "duration": 35280,
              "status": "passed"
            },
            "match": {
              "location": "RpnCalculatorStepdefs.before(Scenario)"
            }
          }
        ],
        "line": 25,
        "name": "Comportamiento",
        "description": "",
        "id": "med-126---obligatorios-numero-42;comportamiento;;2",
        "after": [
          {
            "result": {
              "duration": 24696,
              "status": "passed"
            },
            "match": {
              "location": "RpnCalculatorStepdefs.after(Scenario)"
            }
          }
        ],
        "type": "scenario",
        "keyword": "Scenario Outline",
        "steps": [
          {
            "result": {
              "duration": 14441147255,
              "status": "passed"
            },
            "line": 4,
            "name": "Ingreso al sistema Sume",
            "match": {
              "location": "Test40.ingreso_al_sistema_Sume()"
            },
            "keyword": "Given "
          },
          {
            "result": {
              "duration": 75050652,
              "status": "passed"
            },
            "line": 5,
            "name": "Usuario: mveron",
            "match": {
              "arguments": [
                {
                  "val": "mveron",
                  "offset": 9
                }
              ],
              "location": "Test40.usuario_mveron(String)"
            },
            "keyword": "And "
          },
          {
            "result": {
              "duration": 76833617,
              "status": "passed"
            },
            "line": 6,
            "name": "Pass: Mv190319",
            "match": {
              "arguments": [
                {
                  "val": "Mv190319",
                  "offset": 6
                }
              ],
              "location": "Test40.pass_Mv(String)"
            },
            "keyword": "And "
          },
          {
            "result": {
              "duration": 6262936757,
              "status": "passed"
            },
            "line": 7,
            "name": "Seleccion alta de responsable de pago",
            "match": {
              "location": "Test40.seleccion_alta_de_responsable_de_pago()"
            },
            "keyword": "And "
          },
          {
            "result": {
              "duration": 3379516146,
              "status": "passed"
            },
            "line": 8,
            "name": "Tipo de responsable Empresa",
            "match": {
              "arguments": [
                {
                  "val": "Empresa",
                  "offset": 20
                }
              ],
              "location": "Test40.tipo_de_responsable_Empresa(String)"
            },
            "keyword": "And "
          },
          {
            "result": {
              "duration": 418182647,
              "status": "passed"
            },
            "line": 9,
            "name": "Busqueda de entidad",
            "match": {
              "location": "Test40.busqueda_de_entidad()"
            },
            "keyword": "And "
          },
          {
            "result": {
              "duration": 392357404,
              "status": "passed"
            },
            "line": 10,
            "name": "Ingreso de cuit - Cuil 20107321048",
            "match": {
              "arguments": [
                {
                  "val": "20107321048",
                  "offset": 23
                }
              ],
              "location": "Test40.ingreso_de_cuit_Cuil(String)"
            },
            "keyword": "And "
          },
          {
            "result": {
              "duration": 320430067,
              "status": "passed"
            },
            "line": 11,
            "name": "Ingreso de descripcion PONCE CESAR HERNAN",
            "match": {
              "arguments": [
                {
                  "val": "PONCE CESAR HERNAN",
                  "offset": 23
                }
              ],
              "location": "Test40.ingreso_de_descripcion_BAZAR_AVENIDA(String)"
            },
            "keyword": "And "
          },
          {
            "result": {
              "duration": 2839756422,
              "status": "passed"
            },
            "line": 12,
            "name": "Seleccionar resultado y confimar entidad",
            "match": {
              "location": "Test40.seleccionar_resultado_y_confimar_entidad()"
            },
            "keyword": "And "
          },
          {
            "result": {
              "duration": 256050902,
              "status": "passed"
            },
            "line": 13,
            "name": "Ingreso de fecha de vigencia 04/07/2019",
            "match": {
              "arguments": [
                {
                  "val": "04/07/2019",
                  "offset": 29
                }
              ],
              "location": "Test40.ingreso_de_fecha_de_vigencia(String)"
            },
            "keyword": "And "
          },
          {
            "result": {
              "duration": 221773657,
              "status": "passed"
            },
            "line": 14,
            "name": "Ingreso de correo Mveron@OpenDev.com",
            "match": {
              "arguments": [
                {
                  "val": "Mveron@OpenDev.com",
                  "offset": 18
                }
              ],
              "location": "Test40.ingreso_de_correo_Mveron_OpenDevSolutions_com(String)"
            },
            "keyword": "And "
          },
          {
            "result": {
              "duration": 238782221,
              "status": "passed"
            },
            "line": 15,
            "name": "Seleccion boton confimar",
            "match": {
              "location": "Test40.seleccion_boton_confimar()"
            },
            "keyword": "When "
          },
          {
            "result": {
              "duration": 754689,
              "status": "passed"
            },
            "line": 16,
            "name": "Validacion ingreso a la pantalla de datos fiscales",
            "match": {
              "location": "Test40.validacion_ingreso_a_la_pantalla_de_datos_fiscales()"
            },
            "keyword": "Then "
          },
          {
            "result": {
              "duration": 1631457153,
              "status": "passed"
            },
            "line": 17,
            "name": "Ingreso fecha datos fiscales 04/07/2019",
            "match": {
              "arguments": [
                {
                  "val": "04/07/2019",
                  "offset": 29
                }
              ],
              "location": "Test40.ingreso_fecha_datos_fiscales(String)"
            },
            "keyword": "And "
          },
          {
            "result": {
              "duration": 133965780,
              "status": "passed"
            },
            "line": 18,
            "name": "Seleccion Tipo de pago \"Pago presencial\"",
            "match": {
              "arguments": [
                {
                  "val": "\"Pago presencial\"",
                  "offset": 23
                }
              ],
              "location": "Test40.seleccion_Tipo_de_pago(String)"
            },
            "keyword": "And "
          },
          {
            "result": {
              "duration": 918599441,
              "status": "passed"
            },
            "line": 19,
            "name": "Ingresar nuevo telefono",
            "match": {
              "location": "Test40.ingresar_nuevo_telefono()"
            },
            "keyword": "And "
          },
          {
            "result": {
              "duration": 34923205,
              "status": "passed"
            },
            "line": 20,
            "name": "selecionar confimar datos fisacales",
            "match": {
              "location": "Test40.selecionar_confimar_datos_fisacales()"
            },
            "keyword": "When "
          },
          {
            "result": {
              "duration": 444218,
              "status": "passed"
            },
            "line": 21,
            "name": "Validar pantalla bandeja de entrada",
            "match": {
              "location": "Test40.validar_pantalla_bandeja_de_entrada()"
            },
            "keyword": "Then "
          }
        ]
      },
      {
        "before": [
          {
            "output": [
              "Runs before scenarios *not* tagged with @foo"
            ],
            "result": {
              "duration": 169348,
              "status": "passed"
            },
            "match": {
              "location": "RpnCalculatorStepdefs.before(Scenario)"
            }
          }
        ],
        "line": 26,
        "name": "Comportamiento",
        "description": "",
        "id": "med-126---obligatorios-numero-42;comportamiento;;3",
        "after": [
          {
            "result": {
              "duration": 15716,
              "status": "passed"
            },
            "match": {
              "location": "RpnCalculatorStepdefs.after(Scenario)"
            }
          }
        ],
        "type": "scenario",
        "keyword": "Scenario Outline",
        "steps": [
          {
            "result": {
              "duration": 13497312082,
              "status": "passed"
            },
            "line": 4,
            "name": "Ingreso al sistema Sume",
            "match": {
              "location": "Test40.ingreso_al_sistema_Sume()"
            },
            "keyword": "Given "
          },
          {
            "result": {
              "duration": 76027610,
              "status": "passed"
            },
            "line": 5,
            "name": "Usuario: mponcetta",
            "match": {
              "arguments": [
                {
                  "val": "mponcetta",
                  "offset": 9
                }
              ],
              "location": "Test40.usuario_mveron(String)"
            },
            "keyword": "And "
          },
          {
            "result": {
              "duration": 84994713,
              "status": "passed"
            },
            "line": 6,
            "name": "Pass: Mp190319",
            "match": {
              "arguments": [
                {
                  "val": "Mp190319",
                  "offset": 6
                }
              ],
              "location": "Test40.pass_Mv(String)"
            },
            "keyword": "And "
          },
          {
            "result": {
              "duration": 9555335888,
              "status": "passed"
            },
            "line": 7,
            "name": "Seleccion alta de responsable de pago",
            "match": {
              "location": "Test40.seleccion_alta_de_responsable_de_pago()"
            },
            "keyword": "And "
          },
          {
            "result": {
              "duration": 3293060807,
              "status": "passed"
            },
            "line": 8,
            "name": "Tipo de responsable Empresa",
            "match": {
              "arguments": [
                {
                  "val": "Empresa",
                  "offset": 20
                }
              ],
              "location": "Test40.tipo_de_responsable_Empresa(String)"
            },
            "keyword": "And "
          },
          {
            "result": {
              "duration": 282001872,
              "status": "passed"
            },
            "line": 9,
            "name": "Busqueda de entidad",
            "match": {
              "location": "Test40.busqueda_de_entidad()"
            },
            "keyword": "And "
          },
          {
            "result": {
              "duration": 217162132,
              "status": "passed"
            },
            "line": 10,
            "name": "Ingreso de cuit - Cuil 30679250945",
            "match": {
              "arguments": [
                {
                  "val": "30679250945",
                  "offset": 23
                }
              ],
              "location": "Test40.ingreso_de_cuit_Cuil(String)"
            },
            "keyword": "And "
          },
          {
            "result": {
              "duration": 509249831,
              "status": "passed"
            },
            "line": 11,
            "name": "Ingreso de descripcion INSTITUTO MARIA MADRE NUESTRA",
            "match": {
              "arguments": [
                {
                  "val": "INSTITUTO MARIA MADRE NUESTRA",
                  "offset": 23
                }
              ],
              "location": "Test40.ingreso_de_descripcion_BAZAR_AVENIDA(String)"
            },
            "keyword": "And "
          },
          {
            "result": {
              "duration": 2462479967,
              "status": "passed"
            },
            "line": 12,
            "name": "Seleccionar resultado y confimar entidad",
            "match": {
              "location": "Test40.seleccionar_resultado_y_confimar_entidad()"
            },
            "keyword": "And "
          },
          {
            "result": {
              "duration": 258714925,
              "status": "passed"
            },
            "line": 13,
            "name": "Ingreso de fecha de vigencia 06/07/2019",
            "match": {
              "arguments": [
                {
                  "val": "06/07/2019",
                  "offset": 29
                }
              ],
              "location": "Test40.ingreso_de_fecha_de_vigencia(String)"
            },
            "keyword": "And "
          },
          {
            "result": {
              "duration": 264118985,
              "status": "passed"
            },
            "line": 14,
            "name": "Ingreso de correo Mponceta@OpenDev.com",
            "match": {
              "arguments": [
                {
                  "val": "Mponceta@OpenDev.com",
                  "offset": 18
                }
              ],
              "location": "Test40.ingreso_de_correo_Mveron_OpenDevSolutions_com(String)"
            },
            "keyword": "And "
          },
          {
            "result": {
              "duration": 152865396,
              "status": "passed"
            },
            "line": 15,
            "name": "Seleccion boton confimar",
            "match": {
              "location": "Test40.seleccion_boton_confimar()"
            },
            "keyword": "When "
          },
          {
            "result": {
              "duration": 154595,
              "status": "passed"
            },
            "line": 16,
            "name": "Validacion ingreso a la pantalla de datos fiscales",
            "match": {
              "location": "Test40.validacion_ingreso_a_la_pantalla_de_datos_fiscales()"
            },
            "keyword": "Then "
          },
          {
            "result": {
              "duration": 1193743683,
              "status": "passed"
            },
            "line": 17,
            "name": "Ingreso fecha datos fiscales 03/07/2019",
            "match": {
              "arguments": [
                {
                  "val": "03/07/2019",
                  "offset": 29
                }
              ],
              "location": "Test40.ingreso_fecha_datos_fiscales(String)"
            },
            "keyword": "And "
          },
          {
            "result": {
              "duration": 195913454,
              "status": "passed"
            },
            "line": 18,
            "name": "Seleccion Tipo de pago \"Pago presencial\"",
            "match": {
              "arguments": [
                {
                  "val": "\"Pago presencial\"",
                  "offset": 23
                }
              ],
              "location": "Test40.seleccion_Tipo_de_pago(String)"
            },
            "keyword": "And "
          },
          {
            "result": {
              "duration": 956831987,
              "status": "passed"
            },
            "line": 19,
            "name": "Ingresar nuevo telefono",
            "match": {
              "location": "Test40.ingresar_nuevo_telefono()"
            },
            "keyword": "And "
          },
          {
            "result": {
              "duration": 48945729,
              "status": "passed"
            },
            "line": 20,
            "name": "selecionar confimar datos fisacales",
            "match": {
              "location": "Test40.selecionar_confimar_datos_fisacales()"
            },
            "keyword": "When "
          },
          {
            "result": {
              "duration": 159726,
              "status": "passed"
            },
            "line": 21,
            "name": "Validar pantalla bandeja de entrada",
            "match": {
              "location": "Test40.validar_pantalla_bandeja_de_entrada()"
            },
            "keyword": "Then "
          }
        ]
      },
      {
        "before": [
          {
            "output": [
              "Runs before scenarios *not* tagged with @foo"
            ],
            "result": {
              "duration": 46507,
              "status": "passed"
            },
            "match": {
              "location": "RpnCalculatorStepdefs.before(Scenario)"
            }
          }
        ],
        "line": 27,
        "name": "Comportamiento",
        "description": "",
        "id": "med-126---obligatorios-numero-42;comportamiento;;4",
        "after": [
          {
            "result": {
              "duration": 15395,
              "status": "passed"
            },
            "match": {
              "location": "RpnCalculatorStepdefs.after(Scenario)"
            }
          }
        ],
        "type": "scenario",
        "keyword": "Scenario Outline",
        "steps": [
          {
            "result": {
              "duration": 14190214318,
              "status": "passed"
            },
            "line": 4,
            "name": "Ingreso al sistema Sume",
            "match": {
              "location": "Test40.ingreso_al_sistema_Sume()"
            },
            "keyword": "Given "
          },
          {
            "result": {
              "duration": 69796055,
              "status": "passed"
            },
            "line": 5,
            "name": "Usuario: mciarla",
            "match": {
              "arguments": [
                {
                  "val": "mciarla",
                  "offset": 9
                }
              ],
              "location": "Test40.usuario_mveron(String)"
            },
            "keyword": "And "
          },
          {
            "result": {
              "duration": 88524720,
              "status": "passed"
            },
            "line": 6,
            "name": "Pass: Mc190319",
            "match": {
              "arguments": [
                {
                  "val": "Mc190319",
                  "offset": 6
                }
              ],
              "location": "Test40.pass_Mv(String)"
            },
            "keyword": "And "
          },
          {
            "result": {
              "duration": 7645150282,
              "status": "passed"
            },
            "line": 7,
            "name": "Seleccion alta de responsable de pago",
            "match": {
              "location": "Test40.seleccion_alta_de_responsable_de_pago()"
            },
            "keyword": "And "
          },
          {
            "result": {
              "duration": 3327884263,
              "status": "passed"
            },
            "line": 8,
            "name": "Tipo de responsable Empresa",
            "match": {
              "arguments": [
                {
                  "val": "Empresa",
                  "offset": 20
                }
              ],
              "location": "Test40.tipo_de_responsable_Empresa(String)"
            },
            "keyword": "And "
          },
          {
            "result": {
              "duration": 327703049,
              "status": "passed"
            },
            "line": 9,
            "name": "Busqueda de entidad",
            "match": {
              "location": "Test40.busqueda_de_entidad()"
            },
            "keyword": "And "
          },
          {
            "result": {
              "duration": 219551607,
              "status": "passed"
            },
            "line": 10,
            "name": "Ingreso de cuit - Cuil 30569151763",
            "match": {
              "arguments": [
                {
                  "val": "30569151763",
                  "offset": 23
                }
              ],
              "location": "Test40.ingreso_de_cuit_Cuil(String)"
            },
            "keyword": "And "
          },
          {
            "result": {
              "duration": 346486559,
              "status": "passed"
            },
            "line": 11,
            "name": "Ingreso de descripcion BANCO PIANO S.A.",
            "match": {
              "arguments": [
                {
                  "val": "BANCO PIANO S.A.",
                  "offset": 23
                }
              ],
              "location": "Test40.ingreso_de_descripcion_BAZAR_AVENIDA(String)"
            },
            "keyword": "And "
          },
          {
            "result": {
              "duration": 2478941037,
              "status": "passed"
            },
            "line": 12,
            "name": "Seleccionar resultado y confimar entidad",
            "match": {
              "location": "Test40.seleccionar_resultado_y_confimar_entidad()"
            },
            "keyword": "And "
          },
          {
            "result": {
              "duration": 275251047,
              "status": "passed"
            },
            "line": 13,
            "name": "Ingreso de fecha de vigencia 08/07/2019",
            "match": {
              "arguments": [
                {
                  "val": "08/07/2019",
                  "offset": 29
                }
              ],
              "location": "Test40.ingreso_de_fecha_de_vigencia(String)"
            },
            "keyword": "And "
          },
          {
            "result": {
              "duration": 235080300,
              "status": "passed"
            },
            "line": 14,
            "name": "Ingreso de correo Mciarla@OpenDev.com",
            "match": {
              "arguments": [
                {
                  "val": "Mciarla@OpenDev.com",
                  "offset": 18
                }
              ],
              "location": "Test40.ingreso_de_correo_Mveron_OpenDevSolutions_com(String)"
            },
            "keyword": "And "
          },
          {
            "result": {
              "duration": 147353570,
              "status": "passed"
            },
            "line": 15,
            "name": "Seleccion boton confimar",
            "match": {
              "location": "Test40.seleccion_boton_confimar()"
            },
            "keyword": "When "
          },
          {
            "result": {
              "duration": 148180,
              "status": "passed"
            },
            "line": 16,
            "name": "Validacion ingreso a la pantalla de datos fiscales",
            "match": {
              "location": "Test40.validacion_ingreso_a_la_pantalla_de_datos_fiscales()"
            },
            "keyword": "Then "
          },
          {
            "result": {
              "duration": 1078342673,
              "status": "passed"
            },
            "line": 17,
            "name": "Ingreso fecha datos fiscales 01/07/2019",
            "match": {
              "arguments": [
                {
                  "val": "01/07/2019",
                  "offset": 29
                }
              ],
              "location": "Test40.ingreso_fecha_datos_fiscales(String)"
            },
            "keyword": "And "
          },
          {
            "result": {
              "duration": 172275622,
              "status": "passed"
            },
            "line": 18,
            "name": "Seleccion Tipo de pago \"Pago presencial\"",
            "match": {
              "arguments": [
                {
                  "val": "\"Pago presencial\"",
                  "offset": 23
                }
              ],
              "location": "Test40.seleccion_Tipo_de_pago(String)"
            },
            "keyword": "And "
          },
          {
            "result": {
              "duration": 936159348,
              "status": "passed"
            },
            "line": 19,
            "name": "Ingresar nuevo telefono",
            "match": {
              "location": "Test40.ingresar_nuevo_telefono()"
            },
            "keyword": "And "
          },
          {
            "result": {
              "duration": 49182111,
              "status": "passed"
            },
            "line": 20,
            "name": "selecionar confimar datos fisacales",
            "match": {
              "location": "Test40.selecionar_confimar_datos_fisacales()"
            },
            "keyword": "When "
          },
          {
            "result": {
              "duration": 127332,
              "status": "passed"
            },
            "line": 21,
            "name": "Validar pantalla bandeja de entrada",
            "match": {
              "location": "Test40.validar_pantalla_bandeja_de_entrada()"
            },
            "keyword": "Then "
          }
        ]
      }
    ],
    "name": "Med 126 - Obligatorios numero 42",
    "description": "",
    "id": "med-126---obligatorios-numero-42",
    "keyword": "Feature",
    "uri": "cucumber/examples/java/calculator/Test 40.feature",
    "tags": []
  },
  {
    "line": 2,
    "elements": [
      {
        "line": 4,
        "name": "A Calculator",
        "description": "",
        "type": "background",
        "keyword": "Background",
        "steps": [
          {
            "result": {
              "duration": 763670,
              "status": "passed"
            },
            "line": 5,
            "name": "a calculator I just turned on",
            "match": {
              "location": "RpnCalculatorStepdefs.a_calculator_I_just_turned_on()"
            },
            "keyword": "Given "
          }
        ]
      },
      {
        "line": 7,
        "name": "Addition",
        "description": "",
        "id": "basic-arithmetic;addition",
        "after": [
          {
            "result": {
              "duration": 23414,
              "status": "passed"
            },
            "match": {
              "location": "RpnCalculatorStepdefs.after(Scenario)"
            }
          }
        ],
        "type": "scenario",
        "keyword": "Scenario",
        "steps": [
          {
            "result": {
              "duration": 1185436,
              "status": "passed"
            },
            "line": 9,
            "name": "I add 4 and 5",
            "match": {
              "arguments": [
                {
                  "val": "4",
                  "offset": 6
                },
                {
                  "val": "5",
                  "offset": 12
                }
              ],
              "location": "RpnCalculatorStepdefs.adding(int,int)"
            },
            "keyword": "When "
          },
          {
            "result": {
              "duration": 14281036,
              "status": "passed"
            },
            "line": 10,
            "name": "the result is 9",
            "match": {
              "arguments": [
                {
                  "val": "9",
                  "offset": 14
                }
              ],
              "location": "RpnCalculatorStepdefs.the_result_is(double)"
            },
            "keyword": "Then "
          }
        ],
        "tags": [
          {
            "name": "@foo"
          }
        ]
      },
      {
        "line": 4,
        "name": "A Calculator",
        "description": "",
        "type": "background",
        "keyword": "Background",
        "steps": [
          {
            "result": {
              "duration": 111295,
              "status": "passed"
            },
            "line": 5,
            "name": "a calculator I just turned on",
            "match": {
              "location": "RpnCalculatorStepdefs.a_calculator_I_just_turned_on()"
            },
            "keyword": "Given "
          }
        ]
      },
      {
        "line": 12,
        "name": "Another Addition",
        "description": "",
        "id": "basic-arithmetic;another-addition",
        "after": [
          {
            "result": {
              "duration": 12188,
              "status": "passed"
            },
            "match": {
              "location": "RpnCalculatorStepdefs.after(Scenario)"
            }
          }
        ],
        "type": "scenario",
        "keyword": "Scenario",
        "steps": [
          {
            "result": {
              "duration": 137595,
              "status": "passed"
            },
            "line": 14,
            "name": "I add 4 and 7",
            "match": {
              "arguments": [
                {
                  "val": "4",
                  "offset": 6
                },
                {
                  "val": "7",
                  "offset": 12
                }
              ],
              "location": "RpnCalculatorStepdefs.adding(int,int)"
            },
            "keyword": "When "
          },
          {
            "result": {
              "duration": 92051,
              "status": "passed"
            },
            "line": 15,
            "name": "the result is 11",
            "match": {
              "arguments": [
                {
                  "val": "11",
                  "offset": 14
                }
              ],
              "location": "RpnCalculatorStepdefs.the_result_is(double)"
            },
            "keyword": "Then "
          }
        ],
        "tags": [
          {
            "name": "@foo"
          }
        ]
      },
      {
        "line": 4,
        "name": "A Calculator",
        "description": "",
        "type": "background",
        "keyword": "Background",
        "steps": [
          {
            "result": {
              "duration": 99107,
              "status": "passed"
            },
            "line": 5,
            "name": "a calculator I just turned on",
            "match": {
              "location": "RpnCalculatorStepdefs.a_calculator_I_just_turned_on()"
            },
            "keyword": "Given "
          }
        ]
      },
      {
        "line": 29,
        "name": "Many additions",
        "description": "",
        "id": "basic-arithmetic;many-additions;single-digits;2",
        "after": [
          {
            "result": {
              "duration": 19565,
              "status": "passed"
            },
            "match": {
              "location": "RpnCalculatorStepdefs.after(Scenario)"
            }
          }
        ],
        "type": "scenario",
        "keyword": "Scenario Outline",
        "steps": [
          {
            "result": {
              "duration": 37612887,
              "status": "passed"
            },
            "line": 18,
            "name": "the previous entries:",
            "match": {
              "location": "RpnCalculatorStepdefs.thePreviousEntries(RpnCalculatorStepdefs$Entry\u003e)"
            },
            "rows": [
              {
                "cells": [
                  "first",
                  "second",
                  "operation"
                ]
              },
              {
                "cells": [
                  "1",
                  "1",
                  "+"
                ]
              },
              {
                "cells": [
                  "2",
                  "1",
                  "+"
                ]
              }
            ],
            "keyword": "Given "
          },
          {
            "result": {
              "duration": 1294485,
              "status": "passed"
            },
            "line": 22,
            "name": "I press +",
            "match": {
              "arguments": [
                {
                  "val": "+",
                  "offset": 8
                }
              ],
              "location": "RpnCalculatorStepdefs.I_press(String)"
            },
            "keyword": "When "
          },
          {
            "result": {
              "duration": 719408,
              "status": "passed"
            },
            "line": 23,
            "name": "I add 1 and 2",
            "match": {
              "arguments": [
                {
                  "val": "1",
                  "offset": 6
                },
                {
                  "val": "2",
                  "offset": 12
                }
              ],
              "location": "RpnCalculatorStepdefs.adding(int,int)"
            },
            "keyword": "And "
          },
          {
            "result": {
              "duration": 345110,
              "status": "passed"
            },
            "line": 24,
            "name": "I press +",
            "match": {
              "arguments": [
                {
                  "val": "+",
                  "offset": 8
                }
              ],
              "location": "RpnCalculatorStepdefs.I_press(String)"
            },
            "keyword": "And "
          },
          {
            "result": {
              "duration": 238627,
              "status": "passed"
            },
            "line": 25,
            "name": "the result is 8",
            "match": {
              "arguments": [
                {
                  "val": "8",
                  "offset": 14
                }
              ],
              "location": "RpnCalculatorStepdefs.the_result_is(double)"
            },
            "keyword": "Then "
          }
        ],
        "tags": [
          {
            "name": "@foo"
          }
        ]
      },
      {
        "line": 4,
        "name": "A Calculator",
        "description": "",
        "type": "background",
        "keyword": "Background",
        "steps": [
          {
            "result": {
              "duration": 117389,
              "status": "passed"
            },
            "line": 5,
            "name": "a calculator I just turned on",
            "match": {
              "location": "RpnCalculatorStepdefs.a_calculator_I_just_turned_on()"
            },
            "keyword": "Given "
          }
        ]
      },
      {
        "line": 30,
        "name": "Many additions",
        "description": "",
        "id": "basic-arithmetic;many-additions;single-digits;3",
        "after": [
          {
            "result": {
              "duration": 16037,
              "status": "passed"
            },
            "match": {
              "location": "RpnCalculatorStepdefs.after(Scenario)"
            }
          }
        ],
        "type": "scenario",
        "keyword": "Scenario Outline",
        "steps": [
          {
            "result": {
              "duration": 610359,
              "status": "passed"
            },
            "line": 18,
            "name": "the previous entries:",
            "match": {
              "location": "RpnCalculatorStepdefs.thePreviousEntries(RpnCalculatorStepdefs$Entry\u003e)"
            },
            "rows": [
              {
                "cells": [
                  "first",
                  "second",
                  "operation"
                ]
              },
              {
                "cells": [
                  "1",
                  "1",
                  "+"
                ]
              },
              {
                "cells": [
                  "2",
                  "1",
                  "+"
                ]
              }
            ],
            "keyword": "Given "
          },
          {
            "result": {
              "duration": 381033,
              "status": "passed"
            },
            "line": 22,
            "name": "I press +",
            "match": {
              "arguments": [
                {
                  "val": "+",
                  "offset": 8
                }
              ],
              "location": "RpnCalculatorStepdefs.I_press(String)"
            },
            "keyword": "When "
          },
          {
            "result": {
              "duration": 139841,
              "status": "passed"
            },
            "line": 23,
            "name": "I add 2 and 3",
            "match": {
              "arguments": [
                {
                  "val": "2",
                  "offset": 6
                },
                {
                  "val": "3",
                  "offset": 12
                }
              ],
              "location": "RpnCalculatorStepdefs.adding(int,int)"
            },
            "keyword": "And "
          },
          {
            "result": {
              "duration": 84995,
              "status": "passed"
            },
            "line": 24,
            "name": "I press +",
            "match": {
              "arguments": [
                {
                  "val": "+",
                  "offset": 8
                }
              ],
              "location": "RpnCalculatorStepdefs.I_press(String)"
            },
            "keyword": "And "
          },
          {
            "result": {
              "duration": 219062,
              "status": "passed"
            },
            "line": 25,
            "name": "the result is 10",
            "match": {
              "arguments": [
                {
                  "val": "10",
                  "offset": 14
                }
              ],
              "location": "RpnCalculatorStepdefs.the_result_is(double)"
            },
            "keyword": "Then "
          }
        ],
        "tags": [
          {
            "name": "@foo"
          }
        ]
      },
      {
        "line": 4,
        "name": "A Calculator",
        "description": "",
        "type": "background",
        "keyword": "Background",
        "steps": [
          {
            "result": {
              "duration": 110974,
              "status": "passed"
            },
            "line": 5,
            "name": "a calculator I just turned on",
            "match": {
              "location": "RpnCalculatorStepdefs.a_calculator_I_just_turned_on()"
            },
            "keyword": "Given "
          }
        ]
      },
      {
        "line": 34,
        "name": "Many additions",
        "description": "",
        "id": "basic-arithmetic;many-additions;double-digits;2",
        "after": [
          {
            "result": {
              "duration": 20206,
              "status": "passed"
            },
            "match": {
              "location": "RpnCalculatorStepdefs.after(Scenario)"
            }
          }
        ],
        "type": "scenario",
        "keyword": "Scenario Outline",
        "steps": [
          {
            "result": {
              "duration": 1184795,
              "status": "passed"
            },
            "line": 18,
            "name": "the previous entries:",
            "match": {
              "location": "RpnCalculatorStepdefs.thePreviousEntries(RpnCalculatorStepdefs$Entry\u003e)"
            },
            "rows": [
              {
                "cells": [
                  "first",
                  "second",
                  "operation"
                ]
              },
              {
                "cells": [
                  "1",
                  "1",
                  "+"
                ]
              },
              {
                "cells": [
                  "2",
                  "1",
                  "+"
                ]
              }
            ],
            "keyword": "Given "
          },
          {
            "result": {
              "duration": 225798,
              "status": "passed"
            },
            "line": 22,
            "name": "I press +",
            "match": {
              "arguments": [
                {
                  "val": "+",
                  "offset": 8
                }
              ],
              "location": "RpnCalculatorStepdefs.I_press(String)"
            },
            "keyword": "When "
          },
          {
            "result": {
              "duration": 164858,
              "status": "passed"
            },
            "line": 23,
            "name": "I add 10 and 20",
            "match": {
              "arguments": [
                {
                  "val": "10",
                  "offset": 6
                },
                {
                  "val": "20",
                  "offset": 13
                }
              ],
              "location": "RpnCalculatorStepdefs.adding(int,int)"
            },
            "keyword": "And "
          },
          {
            "result": {
              "duration": 101032,
              "status": "passed"
            },
            "line": 24,
            "name": "I press +",
            "match": {
              "arguments": [
                {
                  "val": "+",
                  "offset": 8
                }
              ],
              "location": "RpnCalculatorStepdefs.I_press(String)"
            },
            "keyword": "And "
          },
          {
            "result": {
              "duration": 229646,
              "status": "passed"
            },
            "line": 25,
            "name": "the result is 35",
            "match": {
              "arguments": [
                {
                  "val": "35",
                  "offset": 14
                }
              ],
              "location": "RpnCalculatorStepdefs.the_result_is(double)"
            },
            "keyword": "Then "
          }
        ],
        "tags": [
          {
            "name": "@foo"
          }
        ]
      },
      {
        "line": 4,
        "name": "A Calculator",
        "description": "",
        "type": "background",
        "keyword": "Background",
        "steps": [
          {
            "result": {
              "duration": 873040,
              "status": "passed"
            },
            "line": 5,
            "name": "a calculator I just turned on",
            "match": {
              "location": "RpnCalculatorStepdefs.a_calculator_I_just_turned_on()"
            },
            "keyword": "Given "
          }
        ]
      },
      {
        "line": 35,
        "name": "Many additions",
        "description": "",
        "id": "basic-arithmetic;many-additions;double-digits;3",
        "after": [
          {
            "result": {
              "duration": 15395,
              "status": "passed"
            },
            "match": {
              "location": "RpnCalculatorStepdefs.after(Scenario)"
            }
          }
        ],
        "type": "scenario",
        "keyword": "Scenario Outline",
        "steps": [
          {
            "result": {
              "duration": 667769,
              "status": "passed"
            },
            "line": 18,
            "name": "the previous entries:",
            "match": {
              "location": "RpnCalculatorStepdefs.thePreviousEntries(RpnCalculatorStepdefs$Entry\u003e)"
            },
            "rows": [
              {
                "cells": [
                  "first",
                  "second",
                  "operation"
                ]
              },
              {
                "cells": [
                  "1",
                  "1",
                  "+"
                ]
              },
              {
                "cells": [
                  "2",
                  "1",
                  "+"
                ]
              }
            ],
            "keyword": "Given "
          },
          {
            "result": {
              "duration": 115144,
              "status": "passed"
            },
            "line": 22,
            "name": "I press +",
            "match": {
              "arguments": [
                {
                  "val": "+",
                  "offset": 8
                }
              ],
              "location": "RpnCalculatorStepdefs.I_press(String)"
            },
            "keyword": "When "
          },
          {
            "result": {
              "duration": 116426,
              "status": "passed"
            },
            "line": 23,
            "name": "I add 20 and 30",
            "match": {
              "arguments": [
                {
                  "val": "20",
                  "offset": 6
                },
                {
                  "val": "30",
                  "offset": 13
                }
              ],
              "location": "RpnCalculatorStepdefs.adding(int,int)"
            },
            "keyword": "And "
          },
          {
            "result": {
              "duration": 73128,
              "status": "passed"
            },
            "line": 24,
            "name": "I press +",
            "match": {
              "arguments": [
                {
                  "val": "+",
                  "offset": 8
                }
              ],
              "location": "RpnCalculatorStepdefs.I_press(String)"
            },
            "keyword": "And "
          },
          {
            "result": {
              "duration": 98466,
              "status": "passed"
            },
            "line": 25,
            "name": "the result is 55",
            "match": {
              "arguments": [
                {
                  "val": "55",
                  "offset": 14
                }
              ],
              "location": "RpnCalculatorStepdefs.the_result_is(double)"
            },
            "keyword": "Then "
          }
        ],
        "tags": [
          {
            "name": "@foo"
          }
        ]
      }
    ],
    "name": "Basic Arithmetic",
    "description": "",
    "id": "basic-arithmetic",
    "keyword": "Feature",
    "uri": "cucumber/examples/java/calculator/basic_arithmetic.feature",
    "tags": [
      {
        "name": "@foo",
        "type": "Tag",
        "location": {
          "line": 1,
          "column": 1
        }
      }
    ]
  },
  {
    "line": 1,
    "elements": [
      {
        "before": [
          {
            "output": [
              "Runs before scenarios *not* tagged with @foo"
            ],
            "result": {
              "duration": 37526,
              "status": "passed"
            },
            "match": {
              "location": "RpnCalculatorStepdefs.before(Scenario)"
            }
          }
        ],
        "line": 5,
        "name": "Determine past date",
        "description": "",
        "id": "dates-with-different-date-formats;determine-past-date",
        "after": [
          {
            "result": {
              "duration": 16998,
              "status": "passed"
            },
            "match": {
              "location": "RpnCalculatorStepdefs.after(Scenario)"
            }
          }
        ],
        "type": "scenario",
        "keyword": "Scenario",
        "steps": [
          {
            "result": {
              "duration": 329716,
              "status": "passed"
            },
            "line": 6,
            "name": "today is 2011-01-20",
            "match": {
              "arguments": [
                {
                  "val": "2011-01-20",
                  "offset": 9
                }
              ],
              "location": "DateStepdefs.today_is(Date)"
            },
            "keyword": "Given "
          },
          {
            "result": {
              "duration": 18889994,
              "status": "passed"
            },
            "line": 7,
            "name": "I ask if Jan 19, 2011 is in the past",
            "match": {
              "arguments": [
                {
                  "val": "Jan 19, 2011",
                  "offset": 9
                }
              ],
              "location": "DateStepdefs.I_ask_if_date_is_in_the_past(Date)"
            },
            "keyword": "When "
          },
          {
            "result": {
              "duration": 163254,
              "status": "passed"
            },
            "line": 8,
            "name": "the result should be yes",
            "match": {
              "arguments": [
                {
                  "val": "yes",
                  "offset": 21
                }
              ],
              "location": "DateStepdefs.the_result_should_be(String)"
            },
            "keyword": "Then "
          }
        ]
      }
    ],
    "name": "Dates with different date formats",
    "description": "  This feature shows you can have different date formats, as long as you annotate the\n  corresponding step definition method accordingly.",
    "id": "dates-with-different-date-formats",
    "keyword": "Feature",
    "uri": "cucumber/examples/java/calculator/date_calculator.feature",
    "tags": []
  },
  {
    "line": 1,
    "elements": [
      {
        "before": [
          {
            "output": [
              "Runs before scenarios *not* tagged with @foo"
            ],
            "result": {
              "duration": 33677,
              "status": "passed"
            },
            "match": {
              "location": "RpnCalculatorStepdefs.before(Scenario)"
            }
          }
        ],
        "line": 3,
        "name": "Give correct change",
        "description": "",
        "id": "shopping;give-correct-change",
        "after": [
          {
            "result": {
              "duration": 47148,
              "status": "passed"
            },
            "match": {
              "location": "RpnCalculatorStepdefs.after(Scenario)"
            }
          }
        ],
        "type": "scenario",
        "keyword": "Scenario",
        "steps": [
          {
            "result": {
              "duration": 5670591,
              "status": "passed"
            },
            "line": 4,
            "name": "the following groceries:",
            "match": {
              "location": "ShoppingStepdefs.the_following_groceries(ShoppingStepdefs$Grocery\u003e)"
            },
            "rows": [
              {
                "cells": [
                  "name",
                  "price"
                ]
              },
              {
                "cells": [
                  "milk",
                  "9"
                ]
              },
              {
                "cells": [
                  "bread",
                  "7"
                ]
              },
              {
                "cells": [
                  "soap",
                  "5"
                ]
              }
            ],
            "keyword": "Given "
          },
          {
            "result": {
              "duration": 752123,
              "status": "passed"
            },
            "line": 9,
            "name": "I pay 25",
            "match": {
              "arguments": [
                {
                  "val": "25",
                  "offset": 6
                }
              ],
              "location": "ShoppingStepdefs.i_pay(int)"
            },
            "keyword": "When "
          },
          {
            "result": {
              "duration": 1135081,
              "status": "passed"
            },
            "line": 10,
            "name": "my change should be 4",
            "match": {
              "arguments": [
                {
                  "val": "4",
                  "offset": 20
                }
              ],
              "location": "ShoppingStepdefs.my_change_should_be_(int)"
            },
            "keyword": "Then "
          }
        ]
      }
    ],
    "name": "Shopping",
    "description": "",
    "id": "shopping",
    "keyword": "Feature",
    "uri": "cucumber/examples/java/calculator/shopping.feature",
    "tags": []
  }
]